setup.py
Gaussian_Binomial_1/Binomialdistribution.py
Gaussian_Binomial_1/Gaussiandistribution.py
Gaussian_Binomial_1/Generaldistribution.py
Gaussian_Binomial_1/__init__.py
Gaussian_Binomial_1.egg-info/PKG-INFO
Gaussian_Binomial_1.egg-info/SOURCES.txt
Gaussian_Binomial_1.egg-info/dependency_links.txt
Gaussian_Binomial_1.egg-info/not-zip-safe
Gaussian_Binomial_1.egg-info/top_level.txt