Metadata-Version: 1.0
Name: Gaussian-Binomial-1
Version: 0.2
Summary: Gaussian and Binomial distributions
Home-page: UNKNOWN
Author: Xu Wang
Author-email: xu.wang.pa@gmail.com
License: UNKNOWN
Platform: UNKNOWN
